LICENSE.txt
MANIFEST.in
README.md
setup.cfg
setup.py
streamexpect.py
streamexpect.egg-info/PKG-INFO
streamexpect.egg-info/SOURCES.txt
streamexpect.egg-info/dependency_links.txt
streamexpect.egg-info/requires.txt
streamexpect.egg-info/top_level.txt
test/test_streamexpect.py