Metadata-Version: 2.1
Name: streamexpect
Version: 0.3.0
Summary: expect-like tools over a Python stream
Home-page: https://github.com/digidotcom/python-streamexpect
Author: Digi International Inc.
Author-email: noreply@digi.com
Keywords: expect pexpect search stream serial pyserial socket
Classifier: Development Status :: 3 - Alpha
Classifier: Environment :: Console
Classifier: Intended Audience :: Developers
Classifier: License :: OSI Approved :: Mozilla Public License 2.0 (MPL 2.0)
Classifier: Operating System :: OS Independent
Classifier: Programming Language :: Python :: 2.7
Classifier: Programming Language :: Python :: 3
Classifier: Programming Language :: Python :: 3.3
Classifier: Programming Language :: Python :: 3.4
Classifier: Programming Language :: Python :: 3.5
Classifier: Programming Language :: Python :: 3.9
Classifier: Programming Language :: Python :: 3.10
Classifier: Topic :: Software Development :: Libraries
License-File: LICENSE.txt
